odoo/addons/l10n_es_account_statement_import_n43/README.rst
odoo/addons/l10n_es_account_statement_import_n43/__init__.py
odoo/addons/l10n_es_account_statement_import_n43/__manifest__.py
odoo/addons/l10n_es_account_statement_import_n43/doc/norma_43_castellano.pdf
odoo/addons/l10n_es_account_statement_import_n43/i18n/ca.po
odoo/addons/l10n_es_account_statement_import_n43/i18n/es.po
odoo/addons/l10n_es_account_statement_import_n43/i18n/eu.po
odoo/addons/l10n_es_account_statement_import_n43/i18n/fr.po
odoo/addons/l10n_es_account_statement_import_n43/i18n/gl.po
odoo/addons/l10n_es_account_statement_import_n43/i18n/l10n_es_account_statement_import_n43.pot
odoo/addons/l10n_es_account_statement_import_n43/i18n/sl.po
odoo/addons/l10n_es_account_statement_import_n43/models/__init__.py
odoo/addons/l10n_es_account_statement_import_n43/models/account_journal.py
odoo/addons/l10n_es_account_statement_import_n43/readme/CONTRIBUTORS.md
odoo/addons/l10n_es_account_statement_import_n43/readme/DESCRIPTION.md
odoo/addons/l10n_es_account_statement_import_n43/readme/ROADMAP.md
odoo/addons/l10n_es_account_statement_import_n43/readme/USAGE.md
odoo/addons/l10n_es_account_statement_import_n43/static/description/icon.png
odoo/addons/l10n_es_account_statement_import_n43/static/description/icon_src.svg
odoo/addons/l10n_es_account_statement_import_n43/static/description/index.html
odoo/addons/l10n_es_account_statement_import_n43/tests/__init__.py
odoo/addons/l10n_es_account_statement_import_n43/tests/test.n43
odoo/addons/l10n_es_account_statement_import_n43/tests/test_l10n_es_account_bank_statement_import_n43.py
odoo/addons/l10n_es_account_statement_import_n43/tests/testmulti.n43
odoo/addons/l10n_es_account_statement_import_n43/views/account_journal_views.xml
odoo/addons/l10n_es_account_statement_import_n43/wizards/__init__.py
odoo/addons/l10n_es_account_statement_import_n43/wizards/account_statement_import_n43.py
odoo_addon_l10n_es_account_statement_import_n43-18.0.1.1.0.1.dist-info/METADATA
odoo_addon_l10n_es_account_statement_import_n43-18.0.1.1.0.1.dist-info/WHEEL
odoo_addon_l10n_es_account_statement_import_n43-18.0.1.1.0.1.dist-info/top_level.txt
odoo_addon_l10n_es_account_statement_import_n43-18.0.1.1.0.1.dist-info/RECORD
