Metadata-Version: 2.1
Name: odoo-addon-l10n_es_account_statement_import_n43
Version: 18.0.1.1.0.1
Requires-Python: >=3.10
Requires-Dist: chardet
Requires-Dist: odoo-addon-account_statement_import_file==18.0.*
Requires-Dist: odoo==18.0.*
Summary: =?utf-8?q?Importaci=C3=B3n_de_extractos_bancarios_espa=C3=B1oles_=28Norma_43=29?=
Home-page: https://github.com/OCA/l10n-spain
License: AGPL-3
Author: Spanish Localization Team,Tecnativa,Odoo Community Association (OCA)
Author-email: support@odoo-community.org
Classifier: Programming Language :: Python
Classifier: Framework :: Odoo
Classifier: Framework :: Odoo :: 18.0
Classifier: License :: OSI Approved :: GNU Affero General Public License v3
Classifier: Development Status :: 6 - Mature
